deepsecure/__init__.py
deepsecure/auth.py
deepsecure/client.py
deepsecure/config.py
deepsecure/exceptions.py
deepsecure/main.py
deepsecure/utils.py
deepsecure/vault.py
deepsecure/commands/__init__.py
deepsecure/commands/agent.py
deepsecure/commands/audit.py
deepsecure/commands/configure.py
deepsecure/commands/deploy.py
deepsecure/commands/harden.py
deepsecure/commands/ide.py
deepsecure/commands/inventory.py
deepsecure/commands/policy.py
deepsecure/commands/risk.py
deepsecure/commands/sandbox.py
deepsecure/commands/scan.py
deepsecure/commands/scorecard.py
deepsecure/commands/vault.py
deepsecure/core/__init__.py
deepsecure/core/agent_client.py
deepsecure/core/audit_client.py
deepsecure/core/audit_logger.py
deepsecure/core/base_client.py
deepsecure/core/config.py
deepsecure/core/deployment_client.py
deepsecure/core/exceptions.py
deepsecure/core/hardening_manager.py
deepsecure/core/identity_manager.py
deepsecure/core/policy_client.py
deepsecure/core/risk_client.py
deepsecure/core/sandbox_manager.py
deepsecure/core/scanner.py
deepsecure/core/schemas.py
deepsecure/core/vault_client.py
deepsecure/core/crypto/__init__.py
deepsecure/core/crypto/key_manager.py
deepsecure_cli-0.0.8.dist-info/licenses/LICENSE
deepsecure_cli-0.0.8.dist-info/METADATA
deepsecure_cli-0.0.8.dist-info/WHEEL
deepsecure_cli-0.0.8.dist-info/entry_points.txt
deepsecure_cli-0.0.8.dist-info/top_level.txt
deepsecure_cli-0.0.8.dist-info/RECORD
