Metadata-Version: 2.4
Name: deepsecure-cli
Version: 0.0.8
Summary: DeepSecure CLI: Secure AI Development Control Plane
Author-email: DeepSecure Team <mahendra@deeptrail.com>
License: Apache-2.0
Project-URL: Homepage, https://github.com/deeptrail/deepsecure-cli
Project-URL: Bug Tracker, https://github.com/deeptrail/deepsecure-cli/issues
Project-URL: Documentation, https://deepsecure.dev/docs
Keywords: security,ai,cli,credentials,vault,policy,sandbox
Classifier: Programming Language :: Python :: 3
Classifier: Programming Language :: Python :: 3.9
Classifier: Programming Language :: Python :: 3.10
Classifier: Programming Language :: Python :: 3.11
Classifier: License :: OSI Approved :: Apache Software License
Classifier: Operating System :: OS Independent
Classifier: Environment :: Console
Classifier: Intended Audience :: Developers
Classifier: Intended Audience :: Information Technology
Classifier: Intended Audience :: System Administrators
Classifier: Topic :: Security
Classifier: Topic :: Software Development :: Libraries :: Python Modules
Requires-Python: >=3.9
License-File: LICENSE
Requires-Dist: typer[all]>=0.9.0
Requires-Dist: rich>=13.0.0
Requires-Dist: keyring>=24.0.0
Requires-Dist: requests>=2.30.0
Requires-Dist: toml>=0.10.2
Requires-Dist: pydantic>=2.0.0
Provides-Extra: dev
Requires-Dist: pytest>=7.0.0; extra == "dev"
Requires-Dist: black>=23.0.0; extra == "dev"
Requires-Dist: mypy>=1.0.0; extra == "dev"
Requires-Dist: isort>=5.0.0; extra == "dev"
Requires-Dist: flake8>=6.0.0; extra == "dev"
Requires-Dist: build>=0.10.0; extra == "dev"
Requires-Dist: twine>=4.0.0; extra == "dev"
Dynamic: license-file
